[
  {
    "name": "Fylde",
    "country": "GB",
    "lat": 53.83333,
    "lng": -2.91667
  },
  {
    "name": "Fyfield",
    "country": "GB",
    "lat": 51.41667,
    "lng": -1.78333
  },
  {
    "name": "Fyteíes",
    "country": "GR",
    "lat": 38.69524,
    "lng": 21.18467
  },
  {
    "name": "Fylí",
    "country": "GR",
    "lat": 38.10235,
    "lng": 23.66901
  },
  {
    "name": "Fyzābād",
    "country": "IN",
    "lat": 26.77549,
    "lng": 82.15018
  },
  {
    "name": "Fyodorov",
    "country": "KZ",
    "lat": 53.63809,
    "lng": 62.69653
  },
  {
    "name": "Fyresdal",
    "country": "NO",
    "lat": 59.18343,
    "lng": 8.0921
  },
  {
    "name": "Fyllinge",
    "country": "SE",
    "lat": 56.65,
    "lng": 12.91667
  },
  {
    "name": "Fyffe",
    "country": "US",
    "lat": 34.44676,
    "lng": -85.90414
  }
]