[
  {
    "name": "Njombé",
    "country": "CM",
    "lat": 4.58056,
    "lng": 9.66472
  },
  {
    "name": "Njinikom",
    "country": "CM",
    "lat": 6.23333,
    "lng": 10.28333
  },
  {
    "name": "Njivice",
    "country": "HR",
    "lat": 45.15806,
    "lng": 14.53861
  },
  {
    "name": "Njoro",
    "country": "KE",
    "lat": -0.33024,
    "lng": 35.94445
  },
  {
    "name": "Njurundabommen",
    "country": "SE",
    "lat": 62.26339,
    "lng": 17.38354
  },
  {
    "name": "Njala",
    "country": "SL",
    "lat": 8.23231,
    "lng": -12.01558
  },
  {
    "name": "Njombe",
    "country": "TZ",
    "lat": -9.34917,
    "lng": 34.77167
  },
  {
    "name": "Njeru",
    "country": "UG",
    "lat": 0.44166,
    "lng": 33.17917
  }
]